fetchtastic/__init__.py
fetchtastic/cli.py
fetchtastic/constants.py
fetchtastic/device_hardware.py
fetchtastic/log_utils.py
fetchtastic/menu_apk.py
fetchtastic/menu_firmware.py
fetchtastic/menu_repo.py
fetchtastic/notifications.py
fetchtastic/repo_downloader.py
fetchtastic/setup_config.py
fetchtastic/utils.py
fetchtastic/download/__init__.py
fetchtastic/download/android.py
fetchtastic/download/base.py
fetchtastic/download/cache.py
fetchtastic/download/cli_integration.py
fetchtastic/download/config_utils.py
fetchtastic/download/files.py
fetchtastic/download/firmware.py
fetchtastic/download/interfaces.py
fetchtastic/download/orchestrator.py
fetchtastic/download/prerelease_history.py
fetchtastic/download/release_history.py
fetchtastic/download/repository.py
fetchtastic/download/version.py
fetchtastic/tools/__init__.py
fetchtastic/tools/setup_fetchtastic.sh
fetchtastic-0.10.2.dist-info/licenses/LICENSE
fetchtastic-0.10.2.dist-info/METADATA
fetchtastic-0.10.2.dist-info/WHEEL
fetchtastic-0.10.2.dist-info/entry_points.txt
fetchtastic-0.10.2.dist-info/top_level.txt
fetchtastic-0.10.2.dist-info/RECORD
