Metadata-Version: 2.4
Name: fetchtastic
Version: 0.10.2
Summary: Meshtastic Firmware and APK Downloader
Author-email: Jeremiah K <jeremiahk@gmx.com>
License-Expression: MIT
Project-URL: Homepage, https://github.com/jeremiah-k/fetchtastic
Project-URL: Repository, https://github.com/jeremiah-k/fetchtastic
Project-URL: Issues, https://github.com/jeremiah-k/fetchtastic/issues
Classifier: Programming Language :: Python :: 3
Classifier: Programming Language :: Python :: 3.10
Classifier: Programming Language :: Python :: 3.11
Classifier: Programming Language :: Python :: 3.12
Classifier: Programming Language :: Python :: 3.13
Classifier: Operating System :: Android
Classifier: Operating System :: POSIX :: Linux
Classifier: Operating System :: MacOS
Classifier: Operating System :: Microsoft :: Windows
Requires-Python: >=3.10
License-File: LICENSE
Requires-Dist: requests
Requires-Dist: pick
Requires-Dist: PyYAML
Requires-Dist: urllib3>=2.0
Requires-Dist: packaging
Requires-Dist: platformdirs==4.5.1
Requires-Dist: rich
Provides-Extra: win
Requires-Dist: pywin32; extra == "win"
Requires-Dist: winshell; extra == "win"
Provides-Extra: test
Requires-Dist: pytest; extra == "test"
Requires-Dist: pytest-mock; extra == "test"
Requires-Dist: pytest-cov; extra == "test"
Dynamic: license-file
